{
  "slug": "为什么有些鸟会把闪亮的东西叼回巢",
  "category": "🐾 动物行为学",
  "subgroup": "",
  "title": "为什么有些鸟会把闪亮的东西叼回巢",
  "outline": [
    {
      "concept": "大多数鸟其实害怕闪亮物体——喜鹊偷亮片的传说是假的，实验证明喜鹊反而回避反光东西。但园丁鸟（bowerbird）是真的会收集亮物，而且它们不是叼回巢，是叼回求偶亭——一个纯粹为了交配搭建的装饰性建筑，跟住处无关。",
      "query": "喜鹊 闪亮 偷 园丁鸟 bowerbird 巢 求偶"
    },
    {
      "concept": "园丁鸟的求偶亭是「扩展表型」——基因表达不限于身体，也延伸到改造环境。雄鸟花数周搭建和装饰这个结构，它没有任何生存功能，唯一的用途就是让雌鸟看了愿意交配。亮物是舞台布景，不是家居用品。",
      "query": "雄鸟 搭建 装饰 建筑 炫耀 build display decorate"
    },
    {
      "concept": "鸟类有四色视觉（含紫外光锥细胞），比人类多看一整个色彩维度。蓝色和反光物体在自然绿棕背景中对比度极高，对鸟眼的视觉冲击远超人眼感受。园丁鸟偏好蓝色瓶盖不是随机审美，是视觉系统对高信号噪声比的天然偏好。",
      "query": "鸟 视觉 蓝色 紫外 颜色 偏好 bird vision UV blue"
    },
    {
      "concept": "雌鸟用求偶亭装饰质量推断雄鸟适合度——这是性选择：能找到并守护大量稀有装饰品的雄鸟，说明觅食能力强、领域好、认知水平高。闪亮物不是鸟的收藏癖，是雄性基因质量的诚实广告，雌鸟用脚投票了上百万年。",
      "query": "雌性 选择 雄性 炫耀 质量 fitness sexual selection mate"
    }
  ],
  "generated_at": "2026-05-22T21:28:01.373731",
  "model": "glm-5.1",
  "fact_check_status": "pending"
}