{
  "slug": "你的狗闻到的世界和你看到的世界复杂度差不多",
  "category": "🐾 动物行为学",
  "subgroup": "",
  "title": "你的狗闻到的世界和你看到的世界复杂度差不多",
  "outline": [
    {
      "concept": "狗的嗅球+梨状皮层占大脑比例，跟人类视觉皮层占大脑比例差不多。不是\"鼻子灵\"这么简单——是整整一个感觉系统占据了同等规模的神经房地产，用差不多的层级处理架构，只是输入通道换成了气味。",
      "query": "狗 闻 嗅觉 大脑 脑区 占比 嗅球"
    },
    {
      "concept": "狗的嗅觉系统会把混合气味拆解成\"气味对象\"，就像视觉把光拆成物体。你闻咖啡是一个味道，狗闻到的是烘焙度、酸度、产地、杯子材质、握过杯子的人的手汗——各自独立的可辨识单元，不是一坨混合物。",
      "query": "狗 分辨 混合气味 区分 不同味道 拆开"
    },
    {
      "concept": "气味会随时间衰减和分层沉积，狗能读出这个梯度。同一个房间，早上的气味和下午不同——温度变化让不同分子挥发速率不同，气流让气味沉积位置偏移。狗闻到的不只是\"什么在哪儿\"，还有\"什么时候在那儿的\"。",
      "query": "狗 闻 时间变化 气味不同 早晚 差异"
    },
    {
      "concept": "犬类能从气味中读取个体身份、情绪状态、健康信息，功能上等于人类看脸。一条狗路过某棵树，能知道谁来过、性别、是否发情、大概多久前、当时的紧张程度——这是社交信息，不是单纯的检测。",
      "query": "狗 闻 认人 情绪 紧张 生病 气味识别"
    },
    {
      "concept": "所以狗进入一个空间时，它经历的不是一个视觉场景加上一些气味提示，而是一个完整的嗅觉场景——有前景有背景、有物体有时间线、有谁在谁走了。复杂度和你推开门一眼扫完整个房间是同等级的，只是它的世界是气味构建的。",
      "query": "狗 进新环境 到处闻 嗅 探索 闻很久"
    }
  ],
  "generated_at": "2026-05-22T21:29:36.355233",
  "model": "glm-5.1",
  "fact_check_status": "pending"
}