{
  "slug": "你的肠道细菌在影响你的心情",
  "category": "🏥 身体与健康",
  "subgroup": "关于健康",
  "title": "你的肠道细菌在影响你的心情",
  "outline": [
    {
      "concept": "肠道细菌直接制造神经递质——你体内约90%的血清素是在肠道合成的，不是大脑。肠道菌群还在生产GABA和多巴胺前体。它们不是消化系统的旁观者，是活跃的化学工厂，产出直接影响你情绪的分子。",
      "query": "肠胃不舒服 心情差 拉肚子 情绪低落 stomach mood"
    },
    {
      "concept": "迷走神经是肠脑之间的物理专线——肠道细菌的代谢产物刺激迷走神经末梢，向脑干发信号。动物实验里，切断迷走神经后，益生菌的情绪调节效果消失。'gut feeling'有真实的解剖学基础。",
      "query": "紧张 胃痛 考试 面试 发抖 nervous stomach anxiety"
    },
    {
      "concept": "菌群失调与情绪障碍是因果关系，不仅是相关性——把抑郁患者的肠道菌群移植给无菌鼠，鼠会表现出抑郁样行为；反过来，特定乳酸杆菌和双歧杆菌的减少稳定地出现在焦虑抑郁患者中。菌群不是旁观者，是参与者。",
      "query": "吃抗生素 情绪变化 肠胃炎 depression antibiotics gut"
    },
    {
      "concept": "饮食在24-72小时内就能显著改变菌群组成——膳食纤维和发酵食品喂养有益菌，高糖高脂压制它们。这意味着通过饮食调整菌群来改善情绪，是一个有生物基础的可操作路径，不是玄学。",
      "query": "吃酸奶 发酵食品 膳食纤维 饮食改变 probiotic food"
    }
  ],
  "generated_at": "2026-05-22T20:49:24.156410",
  "model": "glm-5.1",
  "fact_check_status": "pending"
}