{
  "slug": "炒菜的锅气是什么_一千度的美拉德反应",
  "category": "🍳 食物与烹饪科学",
  "subgroup": "",
  "title": "炒菜的锅气是什么——一千度的美拉德反应",
  "outline": [
    {
      "concept": "锅气不是某种神秘气体，而是食材接触滚烫锅面（200-300°C甚至更高）时瞬间发生的剧烈美拉德反应与焦糖化，产生数百种挥发性风味分子。温度不够，这些反应根本不启动，菜就「没味」。",
      "query": "炒菜 火候不够 不香 没味道"
    },
    {
      "concept": "锅气需要「干」——食材表面水分必须快速蒸发，让锅面温度突破100°C沸点进入美拉德区间。如果菜洗完没沥干就下锅，水分蒸发会吸走大量热，锅温被死死压在100°C，只煮不炒，永远出不了锅气。",
      "query": "蔬菜没沥干 下锅 溅油 出水变煮"
    },
    {
      "concept": "家庭灶火功率远低于餐馆猛火灶，锅温一加食材就骤降，根本达不到美拉德反应的阈值。所以家里炒肉容易出水变煮肉，而不是瞬间焦化锁汁——不是技术差，是热量供给跟不上蒸发和反应的消耗。",
      "query": "家里炒肉 出水变煮 餐馆猛火 锅温不够"
    },
    {
      "concept": "锅气转瞬即逝：美拉德反应的黄金风味窗口很窄，过了就变成焦苦。所以猛火快炒必须十几秒内翻匀出锅，多一秒就从「香」变「糊」。锅气本质上是一种时间敏感的火候艺术，差一秒就是两个世界。",
      "query": "炒菜 多炒一会 就焦了 发苦"
    }
  ],
  "generated_at": "2026-05-22T21:15:30.187419",
  "model": "glm-5.1",
  "fact_check_status": "pending"
}